{"cameraMode":{"drawMode":0,"name":"Shaded","section":"Shading Mode"},"sceneLighting":true,"audioPlay":false,"sceneViewState":{"m_AlwaysRefresh":false,"showFog":true,"showSkybox":true,"showFlares":true,"showImageEffects":true,"showParticleSystems":true,"showVisualEffectGraphs":true,"m_FxEnabled":false},"in2DMode":false,"pivot":{"x":-7.503195762634277,"y":-1.5642249584197999,"z":-0.2344539761543274},"rotation":{"x":0.1929152011871338,"y":-0.8034301400184631,"z":0.43872618675231936,"w":0.353313684463501},"size":13.518607139587403,"orthographic":false}